pycodecov/__init__.py
pycodecov/api/__init__.py
pycodecov/api/api.py
pycodecov/api/branch.py
pycodecov/api/codecov.py
pycodecov/api/owner.py
pycodecov/api/paginated_list.py
pycodecov/api/repo.py
pycodecov/api/user.py
pycodecov/enums/__init__.py
pycodecov/enums/commit_state.py
pycodecov/enums/coverage.py
pycodecov/enums/interval.py
pycodecov/enums/language.py
pycodecov/enums/pull_state.py
pycodecov/enums/service.py
pycodecov/exceptions.py
pycodecov/parsers/__init__.py
pycodecov/parsers/base_commit.py
pycodecov/parsers/base_report.py
pycodecov/parsers/base_total.py
pycodecov/parsers/branch.py
pycodecov/parsers/branch_detail.py
pycodecov/parsers/commit.py
pycodecov/parsers/commit_comparison.py
pycodecov/parsers/commit_coverage.py
pycodecov/parsers/commit_coverage_report.py
pycodecov/parsers/commit_coverage_total.py
pycodecov/parsers/commit_detail.py
pycodecov/parsers/commit_total.py
pycodecov/parsers/component.py
pycodecov/parsers/component_comparison.py
pycodecov/parsers/coverage_trend.py
pycodecov/parsers/diff_comparison.py
pycodecov/parsers/file_change_summary_comparison.py
pycodecov/parsers/file_comparison.py
pycodecov/parsers/file_name_comparison.py
pycodecov/parsers/file_stat_comparison.py
pycodecov/parsers/flag.py
pycodecov/parsers/flag_comparison.py
pycodecov/parsers/git_author.py
pycodecov/parsers/git_commit.py
pycodecov/parsers/line.py
pycodecov/parsers/line_comparison.py
pycodecov/parsers/line_coverage_comparison.py
pycodecov/parsers/line_number_comparison.py
pycodecov/parsers/owner.py
pycodecov/parsers/paginated_list.py
pycodecov/parsers/pull.py
pycodecov/parsers/repo.py
pycodecov/parsers/repo_config.py
pycodecov/parsers/report.py
pycodecov/parsers/report_file.py
pycodecov/parsers/report_total.py
pycodecov/parsers/total_comparison.py
pycodecov/parsers/user.py
pycodecov/py.typed
pycodecov/schemas/__init__.py
pycodecov/schemas/base_commit.py
pycodecov/schemas/base_report_file.py
pycodecov/schemas/base_total.py
pycodecov/schemas/branch.py
pycodecov-0.1.0.dist-info/LICENSE
pycodecov-0.1.0.dist-info/METADATA
pycodecov-0.1.0.dist-info/WHEEL
pycodecov-0.1.0.dist-info/RECORD
