Metadata-Version: 2.1
Name: pycodecov
Version: 0.1.0
Summary: Python Codecov API Wrapper
Home-page: https://github.com/kiraware/pycodecov
License: MIT
Keywords: codecov,api
Author: Kira
Author-email: kiraware@github.com
Maintainer: Kira
Maintainer-email: kiraware@github.com
Requires-Python: >=3.12,<4.0
Classifier: Development Status :: 5 - Production/Stable
Classifier: Environment :: Web Environment
Classifier: Framework :: AsyncIO
Classifier: Framework :: aiohttp
Classifier: Intended Audience :: Developers
Classifier: License :: OSI Approved :: MIT License
Classifier: Operating System :: OS Independent
Classifier: Programming Language :: Python :: 3
Classifier: Programming Language :: Python :: 3.12
Classifier: Topic :: Software Development
Requires-Dist: aiohttp (>=3.9.1,<4.0.0)
Project-URL: Bug Tracker, https://github.com/kiraware/pycodecov/issues
Project-URL: Documentation, https://pycodecov.readthedocs.io/en/latest/
Project-URL: Repository, https://github.com/kiraware/pycodecov
